warmup_scheduler_pytorch/__init__.py
warmup_scheduler_pytorch/warmup_module.py
warmup_scheduler_pytorch-0.1.2.dist-info/LICENSE
warmup_scheduler_pytorch-0.1.2.dist-info/METADATA
warmup_scheduler_pytorch-0.1.2.dist-info/WHEEL
warmup_scheduler_pytorch-0.1.2.dist-info/top_level.txt
warmup_scheduler_pytorch-0.1.2.dist-info/RECORD
