Metadata-Version: 2.1
Name: warmup-scheduler-pytorch
Version: 0.1.2
Summary: A Warmup Scheduler for Pytorch
Home-page: https://github.com/LEFTeyex/warmup
Author: LEFTeyes
Author-email: 1079316858@qq.com
License: UNKNOWN
Project-URL: Bug Tracker, https://github.com/LEFTeyex/warmup/issues
Platform: UNKNOWN
Classifier: Intended Audience :: Science/Research
Classifier: License :: OSI Approved :: MIT License
Classifier: Operating System :: OS Independent
Classifier: Programming Language :: Python :: 3.6
Classifier: Programming Language :: Python :: 3.7
Classifier: Programming Language :: Python :: 3.8
Classifier: Programming Language :: Python :: 3.9
Classifier: Topic :: Scientific/Engineering :: Artificial Intelligence
Requires-Python: >=3.6
License-File: LICENSE
